depcrank/__init__.py
depcrank/analyse.py
depcrank/depcrank_analyse.py
depcrank/depcrank_display.py
depcrank/depcrank_rank.py
depcrank/display.py
depcrank/rank.py
depcrank/utils.py
depcrank/metrics/__init__.py
depcrank/metrics/package-signed.py
depcrank/metrics/popularity.py
depcrank-0.1.0.dist-info/METADATA
depcrank-0.1.0.dist-info/WHEEL
depcrank-0.1.0.dist-info/entry_points.txt
depcrank-0.1.0.dist-info/top_level.txt
depcrank-0.1.0.dist-info/RECORD
