Metadata-Version: 2.1
Name: depcrank
Version: 0.1.0
Summary: Minimal CLI / library to handle dependency information for NYU SSL experiments
Home-page: https://github.com/adityasaky/thesis-tooling
Author: Aditya Sirish
Author-email: aditya.sirish@nyu.edu
License: UNKNOWN
Platform: UNKNOWN
Classifier: Programming Language :: Python :: 3
Classifier: License :: OSI Approved :: GNU General Public License (GPL)
Classifier: Operating System :: OS Independent
Requires-Python: >=3.6
